pHcalc/__init__.py
pHcalc/pHcalc.py
pHcalc-0.2.0.dist-info/METADATA
pHcalc-0.2.0.dist-info/WHEEL
pHcalc-0.2.0.dist-info/top_level.txt
pHcalc-0.2.0.dist-info/RECORD
