Metadata-Version: 2.1
Name: pHcalc
Version: 0.2.0
Summary: Systematic pH calculation package for Python
Author-email: Ryan Nelson <rnelsonchem@gmail.com>
License: BSD-3-Clause
Project-URL: Homepage, https://github.com/rnelsonchem/pHcalc
Keywords: pH,systematic,distribution,titration,acid,base
Classifier: Development Status :: 4 - Beta
Classifier: Intended Audience :: Science/Research
Classifier: License :: OSI Approved :: BSD License
Classifier: Programming Language :: Python :: 3
Requires-Python: >=3.5
Requires-Dist: numpy (>=1.10.0)
Requires-Dist: scipy (>=0.17.0)
Provides-Extra: dev
Requires-Dist: pytest ; extra == 'dev'
Requires-Dist: build ; extra == 'dev'
Requires-Dist: ipython ; extra == 'dev'
Requires-Dist: twine ; extra == 'dev'
Provides-Extra: test
Requires-Dist: pytest ; extra == 'test'
